{"content": {"suites": {"0": {"status": {"total_pass": 0, "total_skip": 0, "total_xpass": 0, "total_xfail": 0, "total_rerun": 0, "total_fail": 1, "total_error": 0}, "tests": {"0": {"status": "FAIL", "message": "   selenium.common.exceptions.StaleElementReferenceException: Message: stale element reference: stale element not found in the current frame\n     (Session info: chrome=124.0.6367.119); For documentation on this error, please visit: https://www.selenium.dev/documentation/webdriver/troubleshooting/errors#stale-element-reference-exception\n   Stacktrace:\n   \tGetHandleVerifier [0x00007FF6E7971502+60802]\n   \t(No symbol) [0x00007FF6E78EAC02]\n   \t(No symbol) [0x00007FF6E77A7CE4]\n   \t(No symbol) [0x00007FF6E77ADE26]\n   \t(No symbol) [0x00007FF6E77B01DB]\n   \t(No symbol) [0x00007FF6E77B0280]\n   \t(No symbol) [0x00007FF6E77F8D14]\n   \t(No symbol) [0x00007FF6E77F7D37]\n   \t(No symbol) [0x00007FF6E77EAE8B]\n   \t(No symbol) [0x00007FF6E781AB7A]\n   \t(No symbol) [0x00007FF6E77EA7C6]\n   \t(No symbol) [0x00007FF6E781AD90]\n   \t(No symbol) [0x00007FF6E783A224]\n   \t(No symbol) [0x00007FF6E781A923]\n   \t(No symbol) [0x00007FF6E77E8FEC]\n   \t(No symbol) [0x00007FF6E77E9C21]\n   \tGetHandleVerifier [0x00007FF6E7C7411D+3217821]\n   \tGetHandleVerifier [0x00007FF6E7CB60B7+3488055]\n   \tGetHandleVerifier [0x00007FF6E7CAF03F+3459263]\n   \tGetHandleVerifier [0x00007FF6E7A2B846+823494]\n   \t(No symbol) [0x00007FF6E78F5F9F]\n   \t(No symbol) [0x00007FF6E78F0EC4]\n   \t(No symbol) [0x00007FF6E78F1052]\n   \t(No symbol) [0x00007FF6E78E18A4]\n   \tBaseThreadInitThunk [0x00007FF80AD7257D+29]\n   \tRtlUserThreadStart [0x00007FF80BCAAA48+40]\n", "test_name": "test_minSixDigitPassword", "rerun": "0"}}, "suite_name": "Test_passwordUpdate.py"}}}, "date": "May 06, 2024", "start_time": 1714968582.6189423, "total_suite": 1, "status": "FAIL", "status_list": {"pass": "0", "fail": "1", "skip": "0", "error": "0", "xpass": "0", "xfail": "0", "rerun": "0"}, "total_tests": "1"}